{
	"materials": [],
	"meshes": [
		{
			"name": "tree1",
			"id": "ef413192-f2b3-4ca2-b8c8-dfd01ff94162",
			"uniqueId": 1722,
			"type": "Mesh",
			"position": [
				0,
				0,
				0
			],
			"rotationQuaternion": [
				0,
				0,
				0,
				1
			],
			"scaling": [
				1,
				1,
				1
			],
			"pivotMatrix": {
				"0": 1,
				"1": 0,
				"2": 0,
				"3": 0,
				"4": 0,
				"5": 1,
				"6": 0,
				"7": 0,
				"8": 0,
				"9": 0,
				"10": 1,
				"11": 0,
				"12": 0,
				"13": 0,
				"14": 0,
				"15": 1
			},
			"isEnabled": true,
			"isVisible": true,
			"infiniteDistance": false,
			"pickable": true,
			"receiveShadows": false,
			"billboardMode": 0,
			"visibility": 1,
			"checkCollisions": false,
			"isBlocker": false,
			"overrideMaterialSideOrientation": 0,
			"parentId": "c628ed56-045c-4807-98d2-8fa0a13f9c2b",
			"isUnIndexed": false,
			"geometryUniqueId": 1319,
			"geometryId": "5d9be5b8-5aa9-4f55-8925-aafacae5f56f",
			"subMeshes": null,
			"materialUniqueId": 2024,
			"materialId": "62cb76cb-a4dc-4a46-bf10-02a67f9b07d4",
			"metadata": {
				"gltf": {
					"pointers": [
						"/meshes/0/primitives/0",
						"/nodes/0"
					]
				},
				"basePoseMatrix": {
					"0": -1,
					"1": 0,
					"2": 0,
					"3": 0,
					"4": 0,
					"5": 1,
					"6": 0,
					"7": 0,
					"8": 0,
					"9": 0,
					"10": 1,
					"11": 0,
					"12": 0,
					"13": 0,
					"14": 0,
					"15": 1
				},
				"originalSourceFile": {
					"id": "tree1",
					"name": "tree1",
					"sceneFileName": "models/BabylonJS Graveyard Assets/Assets-meshes-graveYardPack/tree1/tree1.glb"
				},
				"isPickable": true,
				"script": {
					"name": "None"
				},
				"renderingGroupId": 0,
				"doNotExport": false
			},
			"instances": [],
			"animations": [],
			"ranges": [],
			"layerMask": 268435455,
			"alphaIndex": 1.7976931348623157e+308,
			"hasVertexAlpha": false,
			"overlayAlpha": 0.3,
			"overlayColor": [
				1,
				0,
				0
			],
			"applyFog": true,
			"delayLoadingFile": "geometries/5d9be5b8-5aa9-4f55-8925-aafacae5f56f.babylonbinarymeshdata",
			"boundingBoxMaximum": [
				1.863528847694397,
				4.122812271118164,
				1.3202379941940308
			],
			"boundingBoxMinimum": [
				-1.4078943729400635,
				-0.226182222366333,
				-1.0399881601333618
			],
			"_binaryInfo": {
				"positionsAttrDesc": {
					"count": 9978,
					"stride": 3,
					"offset": 0,
					"dataType": 1
				},
				"normalsAttrDesc": {
					"count": 9978,
					"stride": 3,
					"offset": 39912,
					"dataType": 1
				},
				"uvsAttrDesc": {
					"count": 6652,
					"stride": 2,
					"offset": 79824,
					"dataType": 1
				},
				"indicesAttrDesc": {
					"count": 3504,
					"stride": 1,
					"offset": 106432,
					"dataType": 0
				},
				"subMeshesAttrDesc": {
					"count": 1,
					"stride": 5,
					"offset": 120448,
					"dataType": 0
				}
			},
			"positions": null,
			"normals": null,
			"uvs": null,
			"hasUVs": true,
			"indices": null
		}
	],
	"multiMaterials": [],
	"lods": []
}